coinprecio/__init__.py
coinprecio/__version__.py
coinprecio/coinapi.py
coinprecio/currencies.py
coinprecio/exceptions.py
coinprecio/symbols.py
coinprecio-0.1.1.dist-info/LICENSE
coinprecio-0.1.1.dist-info/METADATA
coinprecio-0.1.1.dist-info/WHEEL
coinprecio-0.1.1.dist-info/top_level.txt
coinprecio-0.1.1.dist-info/RECORD
